ollama_manager/__init__.py
ollama_manager/app.py
ollama_manager/commands/__init__.py
ollama_manager/commands/delete.py
ollama_manager/commands/list.py
ollama_manager/commands/pull.py
ollama_manager/commands/run.py
ollama_manager/ui/__init__.py
ollama_manager/ui/image_chat.py
ollama_manager/ui/text_chat.py
ollama_manager/utils/__init__.py
ollama_manager-0.1.7.dist-info/METADATA
ollama_manager-0.1.7.dist-info/WHEEL
ollama_manager-0.1.7.dist-info/entry_points.txt
ollama_manager-0.1.7.dist-info/top_level.txt
ollama_manager-0.1.7.dist-info/RECORD
