Metadata-Version: 2.4
Name: ollama_manager
Version: 0.1.7
Summary: Manage Ollama models from your commandline!
Author: Yankee Maharjan
Project-URL: Repository, https://github.com/yankeexe/ollama-manager
Keywords: ollama,ollama cli,ollama python,ollama manager
Classifier: Programming Language :: Python :: 3.11
Classifier: Intended Audience :: Developers
Classifier: Development Status :: 3 - Alpha
Requires-Python: >=3.11
Requires-Dist: beautifulsoup4==4.13.4
Requires-Dist: click==8.2.0
Requires-Dist: httpx==0.28.1
Requires-Dist: ollama==0.5.1
Requires-Dist: requests==2.32.4
Requires-Dist: simple-term-menu==1.6.4
Requires-Dist: textual==3.5.0
Provides-Extra: dev
Requires-Dist: ruff==0.7.4; extra == "dev"
Provides-Extra: ui
Requires-Dist: streamlit==1.45.1; extra == "ui"
